sparkfly_client/__init__.py
sparkfly_client/__version__.py
sparkfly_client/client.py
sparkfly_client/errors.py
sparkfly_client/types.py
sparkfly_client/api/__init__.py
sparkfly_client-1.0.0.dist-info/LICENSE
sparkfly_client-1.0.0.dist-info/METADATA
sparkfly_client-1.0.0.dist-info/WHEEL
sparkfly_client-1.0.0.dist-info/top_level.txt
sparkfly_client-1.0.0.dist-info/RECORD
