Metadata-Version: 2.1
Name: sparkfly-client
Version: 1.0.0
Summary: A Python client library for Sparkfly
Home-page: https://github.com/j-madrone/sparkfly
Author: Express Integrations
Author-email: jasper@expressintegrations.com
License: MIT
Classifier: Programming Language :: Python :: 3.8
Classifier: Operating System :: OS Independent
Requires-Python: >=3.8
License-File: LICENSE
Requires-Dist: httpx (==0.25.0)
Requires-Dist: attrs (==21.3.0)
Requires-Dist: python-dateutil (==2.8.2)
